README.txt
setup.py
docs/HISTORY.txt
docs/INSTALL.txt
docs/LICENSE.GPL
docs/LICENSE.txt
webcouturier/__init__.py
webcouturier.hosting.theme.egg-info/PKG-INFO
webcouturier.hosting.theme.egg-info/SOURCES.txt
webcouturier.hosting.theme.egg-info/dependency_links.txt
webcouturier.hosting.theme.egg-info/entry_points.txt
webcouturier.hosting.theme.egg-info/namespace_packages.txt
webcouturier.hosting.theme.egg-info/not-zip-safe
webcouturier.hosting.theme.egg-info/requires.txt
webcouturier.hosting.theme.egg-info/top_level.txt
webcouturier/hosting/__init__.py
webcouturier/hosting/theme/__init__.py
webcouturier/hosting/theme/configure.zcml
webcouturier/hosting/theme/profiles.zcml
webcouturier/hosting/theme/setuphandlers.py
webcouturier/hosting/theme/skins.zcml
webcouturier/hosting/theme/tests.py
webcouturier/hosting/theme/version.txt
webcouturier/hosting/theme/browser/__init__.py
webcouturier/hosting/theme/browser/configure.zcml
webcouturier/hosting/theme/browser/interfaces.py
webcouturier/hosting/theme/browser/viewlets.py
webcouturier/hosting/theme/browser/templates/dashboard.pt
webcouturier/hosting/theme/browser/templates/manage-dashboard.pt
webcouturier/hosting/theme/browser/templates/personal_bar.pt
webcouturier/hosting/theme/browser/templates/searchbox.pt
webcouturier/hosting/theme/browser/templates/sections.pt
webcouturier/hosting/theme/browser/templates/webcouturier_topnavigation.pt
webcouturier/hosting/theme/profiles/default/actions.xml
webcouturier/hosting/theme/profiles/default/cssregistry.xml
webcouturier/hosting/theme/profiles/default/import_steps.xml
webcouturier/hosting/theme/profiles/default/kupu.xml
webcouturier/hosting/theme/profiles/default/skins.xml
webcouturier/hosting/theme/profiles/default/viewlets.xml
webcouturier/hosting/theme/profiles/default/webcouturier.hosting.theme_various.txt
webcouturier/hosting/theme/profiles/tableless/actions.xml
webcouturier/hosting/theme/profiles/tableless/cssregistry.xml
webcouturier/hosting/theme/profiles/tableless/import_steps.xml
webcouturier/hosting/theme/profiles/tableless/kupu.xml
webcouturier/hosting/theme/profiles/tableless/skins.xml
webcouturier/hosting/theme/profiles/tableless/viewlets.xml
webcouturier/hosting/theme/profiles/tableless/webcouturier.hosting.theme_various.txt
webcouturier/hosting/theme/skins/webcouturier_hosting_custom_images/bg_main.gif
