Metadata-Version: 1.0
Name: webcouturier.hosting.theme
Version: 1.0
Summary: Web Couturier Hosting Theme
Home-page: http://www.webcouturier.com
Author: Denys Mishunov
Author-email: denis@webcouturier.com
License: GPL
Keywords: web couturier plone theme
Platform: UNKNOWN
Classifier: Framework :: Plone
Classifier: Framework :: Zope2
Classifier: Framework :: Zope3
Classifier: Programming Language :: Python
Classifier: Topic :: Software Development :: Libraries :: Python Modules
